wifi_monitoring_util/__init__.py
wifi_monitoring_util/airesponses.py
wifi_monitoring_util/dataplot.py
wifi_monitoring_util/log.py
wifi_monitoring_util/logreader.py
wifi_monitoring_util/ui.py
wifi_monitoring_util-0.1.3.2.dist-info/LICENSE
wifi_monitoring_util-0.1.3.2.dist-info/METADATA
wifi_monitoring_util-0.1.3.2.dist-info/WHEEL
wifi_monitoring_util-0.1.3.2.dist-info/entry_points.txt
wifi_monitoring_util-0.1.3.2.dist-info/top_level.txt
wifi_monitoring_util-0.1.3.2.dist-info/RECORD
